dependencias_libs/__init__.py
dependencias_libs-0.1.0.dist-info/METADATA
dependencias_libs-0.1.0.dist-info/WHEEL
dependencias_libs-0.1.0.dist-info/top_level.txt
dependencias_libs-0.1.0.dist-info/RECORD
