Metadata-Version: 2.2
Name: dependencias_libs
Version: 0.1.0
Summary: Pacote de dependências que baixa e prepara o libtorch
Author: Seu Nome
Author-email: seu.email@exemplo.com
Dynamic: author
Dynamic: author-email
Dynamic: summary
